hexathon/__init__.py
hexathon/parse.py
hexathon-0.0.1a4.dist-info/LICENSE.txt
hexathon-0.0.1a4.dist-info/METADATA
hexathon-0.0.1a4.dist-info/WHEEL
hexathon-0.0.1a4.dist-info/top_level.txt
hexathon-0.0.1a4.dist-info/RECORD
