Metadata-Version: 2.1
Name: hexathon
Version: 0.0.1a4
Summary: Common and uncommon hex string operations
Home-page: https://gitlab.com/nolash/python-hexathon
Author: Louis Holbrook
Author-email: dev@holbrook.no
License: GPL3
Keywords: hex
Platform: UNKNOWN
Classifier: Programming Language :: Python :: 3
Classifier: Operating System :: OS Independent
Classifier: Development Status :: 3 - Alpha
Classifier: Topic :: Software Development :: Libraries
Classifier: Intended Audience :: Developers
Classifier: License :: OSI Approved :: GNU General Public License v3 or later (GPLv3+)
Requires-Python: >=3.6
